proyo/__init__.py
proyo/__main__.py
proyo/macros.py
proyo/misc.py
proyo/proyo.py
proyo/script_locals.py
proyo/macros/_.subparsers._
proyo/templates/_.subparsers._
proyo/templates/create/LICENSE
proyo/templates/create/README.md
proyo/templates/create/_._
proyo/templates/create/_.subparsers._
proyo/templates/create/cpp/_._
proyo/templates/create/cpp/_.subparsers._
proyo/templates/create/cpp/app/CMakeLists.txt
proyo/templates/create/cpp/app/meson.build
proyo/templates/create/cpp/app/source/main.cpp
proyo/templates/create/cpp/app/source/meson.build
proyo/templates/create/python/.gitignore
proyo/templates/create/python/.pre-commit-config.yaml
proyo/templates/create/python/README.md
proyo/templates/create/python/_._
proyo/templates/create/python/pyproject.toml
proyo/templates/create/python/{{module_name}}.py
proyo/templates/create/python/tests/test_{{underscore_name}}.py
proyo/templates/create/python/{{package_name}}/__init__.py
proyo/templates/create/python/{{package_name}}/__main__.py
proyo/templates/create/react/_.subparsers._
proyo/templates/create/react/app/.gitignore
proyo/templates/create/react/app/_._
proyo/templates/create/react/app/package.json
proyo/templates/create/react/app/public/favicon.ico
proyo/templates/create/react/app/public/index.html
proyo/templates/create/react/app/public/manifest.json
proyo/templates/create/react/app/src/App.css
proyo/templates/create/react/app/src/App.js
proyo/templates/create/react/app/src/App.test.js
proyo/templates/create/react/app/src/index.css
proyo/templates/create/react/app/src/index.js
proyo-0.2.6.dist-info/LICENSE
proyo-0.2.6.dist-info/METADATA
proyo-0.2.6.dist-info/WHEEL
proyo-0.2.6.dist-info/entry_points.txt
proyo-0.2.6.dist-info/top_level.txt
proyo-0.2.6.dist-info/RECORD
