Metadata-Version: 2.1
Name: proyo
Version: 0.2.6
Summary: A tool to broadcast notifications across various interfaces
Home-page: https://github.com/matthewscholefield/proyo
Author: Matthew Scholefield
Author-email: matthew331199@gmail.com
Keywords: notify server
Classifier: Development Status :: 3 - Alpha
Classifier: Intended Audience :: Developers
Classifier: Programming Language :: Python :: 3
Classifier: Programming Language :: Python :: 3.9
Classifier: Programming Language :: Python :: 3.10
Classifier: Programming Language :: Python :: 3.11
Classifier: Programming Language :: Python :: 3.12
Classifier: Programming Language :: Python :: 3.13
Classifier: License :: OSI Approved :: MIT License
License-File: LICENSE
Requires-Dist: setuptools
